maas_api/__init__.py
maas_api/client.py
maas_api-0.1.1.dist-info/WHEEL
maas_api-0.1.1.dist-info/METADATA
maas_api-0.1.1.dist-info/RECORD
