Metadata-Version: 2.1
Name: maas-api
Version: 0.1.1
Summary: An api client library for MAAS.io
Home-page: https://github.com/jellehelsen/maas-api
Author: Jelle Helsen
Author-email: jelle.helsen@hcode.be
Requires-Python: >=3.9,<4.0
Classifier: Programming Language :: Python :: 3
Classifier: Programming Language :: Python :: 3.10
Classifier: Programming Language :: Python :: 3.9
Requires-Dist: requests (>=2.26,<3.0)
Requires-Dist: requests-oauthlib (>=1.3,<2.0)
